projects/test/src/rtl/test.v
module test (
    input  wire clk,
    input  wire rst_n,
    input  wire [7:0] a,
    input  wire [7:0] b,
    output reg  [8:0] y
);

always @(posedge clk or negedge rst_n) begin
    if (!rst_n)
        y <= 0;
    else
        y <= a + b;
end

endmodule

projects/test/src/tb/tb_test.v
`timescale 1ns/1ps

module tb_test;

reg clk;
reg rst_n;
reg [7:0] a;
reg [7:0] b;
wire [8:0] y;

test dut (
    .clk(clk),
    .rst_n(rst_n),
    .a(a),
    .b(b),
    .y(y)
);

always #5 clk = ~clk;

initial begin
    $dumpfile("src/tb/test.vcd");
    $dumpvars(0, tb_test);

    clk = 0;
    rst_n = 0;
    a = 0;
    b = 0;

    #20 rst_n = 1;
    #10 a = 8'd10;  b = 8'd20;
    #10 a = 8'd5;   b = 8'd7;
    #10 a = 8'd100; b = 8'd50;
    #10 a = 8'd255; b = 8'd1;
    #50 $finish;
end

endmodule

projects/test/src/tb/test.vcd
$date
	Fri May 22 08:22:43 2026
$end
$version
	Icarus Verilog
$end
$timescale
	1ps
$end
$scope module tb_test $end
$var wire 9 ! y [8:0] $end
$var reg 8 " a [7:0] $end
$var reg 8 # b [7:0] $end
$var reg 1 $ clk $end
$var reg 1 % rst_n $end
$scope module dut $end
$var wire 8 & a [7:0] $end
$var wire 8 ' b [7:0] $end
$var wire 1 $ clk $end
$var wire 1 % rst_n $end
$var reg 9 ( y [8:0] $end
$upscope $end
$upscope $end
$enddefinitions $end
#0
$dumpvars
b0 (
b0 '
b0 &
0%
0$
b0 #
b0 "
b0 !
$end
#5000
1$
#10000
0$
#15000
1$
#20000
0$
1%
#25000
1$
#30000
0$
b10100 #
b10100 '
b1010 "
b1010 &
#35000
b11110 !
b11110 (
1$
#40000
0$
b111 #
b111 '
b101 "
b101 &
#45000
b1100 !
b1100 (
1$
#50000
0$
b110010 #
b110010 '
b1100100 "
b1100100 &
#55000
b10010110 !
b10010110 (
1$
#60000
0$
b1 #
b1 '
b11111111 "
b11111111 &
#65000
b100000000 !
b100000000 (
1$
